django_signer/__init__.py
django_signer/core/__init__.py
django_signer/core/signing.py
django_signer/test/__init__.py
django_signer/test/tests.py
django_signer/test/utils.py
django_signer/utils/__init__.py
django_signer/utils/crypto.py
django_signer/utils/encoding.py
django_signer/utils/functional.py
django_signer/utils/regex_helper.py
django_signer-0.2.0.dist-info/LICENSE.python
django_signer-0.2.0.dist-info/LICENSE
django_signer-0.2.0.dist-info/WHEEL
django_signer-0.2.0.dist-info/METADATA
django_signer-0.2.0.dist-info/RECORD
